[{"time": "2021-06-02 05:36:37.305244", "machine": "csd3", "data": [{"Create boundary conditions": 0.076859, "Create RHS function": 0.416276, "Assemble matrix": 5.442905, "Assemble vector": 0.198823, "Create Mesh": 9.294912, "FunctionSpace": 0.548855, "Solve": 61.120872, "problem": "Elastic", "nodes": 16}, {"Create boundary conditions": 0.064601, "Create RHS function": 0.406624, "Assemble matrix": 4.789232, "Assemble vector": 0.200348, "Create Mesh": 6.339899, "FunctionSpace": 0.342621, "Solve": 44.216122, "problem": "Elastic", "nodes": 1}, {"Create boundary conditions": 0.073989, "Create RHS function": 0.447588, "Assemble matrix": 5.31021, "Assemble vector": 0.202025, "Create Mesh": 6.807452, "FunctionSpace": 0.465553, "Solve": 51.426059, "problem": "Elastic", "nodes": 2}, {"Create boundary conditions": 0.073538, "Create RHS function": 0.413868, "Assemble matrix": 5.26215, "Assemble vector": 0.19603, "Create Mesh": 7.280438, "FunctionSpace": 0.462606, "Solve": 54.558529, "problem": "Elastic", "nodes": 4}, {"Create boundary conditions": 0.073239, "Create RHS function": 0.40865, "Assemble matrix": 4.97629, "Assemble vector": 0.193898, "Create Mesh": 8.38916, "FunctionSpace": 0.447526, "Solve": 51.677091, "problem": "Elastic", "nodes": 8}, {"Create boundary conditions": 0.228822, "Create RHS function": 1.61851, "Assemble matrix": 2.902275, "Assemble vector": 0.459917, "Create Mesh": 22.364804, "FunctionSpace": 1.657725, "Solve": 36.665355, "problem": "Poisson", "nodes": 16}, {"Create boundary conditions": 0.221204, "Create RHS function": 1.533162, "Assemble matrix": 2.511715, "Assemble vector": 0.435539, "Create Mesh": 14.3094, "FunctionSpace": 1.237524, "Solve": 24.657937, "problem": "Poisson", "nodes": 1}, {"Create boundary conditions": 0.222767, "Create RHS function": 1.546404, "Assemble matrix": 2.544819, "Assemble vector": 0.441065, "Create Mesh": 15.180845, "FunctionSpace": 1.209653, "Solve": 30.786474, "problem": "Poisson", "nodes": 2}, {"Create boundary conditions": 0.228061, "Create RHS function": 1.641082, "Assemble matrix": 2.8211, "Assemble vector": 0.473566, "Create Mesh": 17.652407, "FunctionSpace": 1.358143, "Solve": 32.411596, "problem": "Poisson", "nodes": 4}, {"Create boundary conditions": 0.226278, "Create RHS function": 1.582269, "Assemble matrix": 2.608726, "Assemble vector": 0.451144, "Create Mesh": 16.559005, "FunctionSpace": 1.46214, "Solve": 30.87125, "problem": "Poisson", "nodes": 8}]}, {"time": "2021-06-04 05:37:00.978738", "machine": "csd3", "data": [{"Create boundary conditions": 0.074703, "Create RHS function": 0.411381, "Assemble matrix": 5.054091, "Assemble vector": 0.195504, "Create Mesh": 8.806664, "FunctionSpace": 0.494872, "Solve": 53.89473, "problem": "Elastic", "nodes": 16}, {"Create boundary conditions": 0.063884, "Create RHS function": 0.404816, "Assemble matrix": 4.902736, "Assemble vector": 0.201535, "Create Mesh": 5.170329, "FunctionSpace": 0.346815, "Solve": 45.085055, "problem": "Elastic", "nodes": 1}, {"Create boundary conditions": 0.073599, "Create RHS function": 0.401855, "Assemble matrix": 4.813351, "Assemble vector": 0.189711, "Create Mesh": 6.254522, "FunctionSpace": 0.417661, "Solve": 46.670992, "problem": "Elastic", "nodes": 2}, {"Create boundary conditions": 0.072951, "Create RHS function": 0.40245, "Assemble matrix": 4.845997, "Assemble vector": 0.190318, "Create Mesh": 7.06098, "FunctionSpace": 0.425766, "Solve": 52.151937, "problem": "Elastic", "nodes": 4}, {"Create boundary conditions": 0.073293, "Create RHS function": 0.40874, "Assemble matrix": 5.187082, "Assemble vector": 0.194269, "Create Mesh": 8.450017, "FunctionSpace": 0.453094, "Solve": 51.515701, "problem": "Elastic", "nodes": 8}, {"Create boundary conditions": 0.226335, "Create RHS function": 1.587191, "Assemble matrix": 2.668681, "Assemble vector": 0.448276, "Create Mesh": 20.259842, "FunctionSpace": 1.505278, "Solve": 33.209226, "problem": "Poisson", "nodes": 16}, {"Create boundary conditions": 0.217913, "Create RHS function": 1.522987, "Assemble matrix": 2.456887, "Assemble vector": 0.431631, "Create Mesh": 14.032369, "FunctionSpace": 1.176912, "Solve": 24.033604, "problem": "Poisson", "nodes": 1}, {"Create boundary conditions": 0.21595, "Create RHS function": 1.545176, "Assemble matrix": 2.524111, "Assemble vector": 0.435575, "Create Mesh": 14.506035, "FunctionSpace": 1.209353, "Solve": 30.204129, "problem": "Poisson", "nodes": 2}, {"Create boundary conditions": 0.219911, "Create RHS function": 1.557881, "Assemble matrix": 2.583889, "Assemble vector": 0.435049, "Create Mesh": 15.597913, "FunctionSpace": 1.283925, "Solve": 31.220097, "problem": "Poisson", "nodes": 4}, {"Create boundary conditions": 0.228034, "Create RHS function": 1.582998, "Assemble matrix": 2.627373, "Assemble vector": 0.447186, "Create Mesh": 16.997543, "FunctionSpace": 1.476716, "Solve": 30.659157, "problem": "Poisson", "nodes": 8}]}, {"time": "2021-06-05 10:42:50.182371", "machine": "csd3", "data": [{"Create boundary conditions": 0.074048, "Create RHS function": 0.413453, "Assemble matrix": 5.50493, "Assemble vector": 0.198289, "Create Mesh": 8.929987, "FunctionSpace": 0.556112, "Solve": 58.436842, "problem": "Elastic", "nodes": 16}, {"Create boundary conditions": 0.065181, "Create RHS function": 0.404713, "Assemble matrix": 4.898965, "Assemble vector": 0.198857, "Create Mesh": 5.441122, "FunctionSpace": 0.35152, "Solve": 44.441832, "problem": "Elastic", "nodes": 1}, {"Create boundary conditions": 0.075488, "Create RHS function": 0.39974, "Assemble matrix": 4.666801, "Assemble vector": 0.190964, "Create Mesh": 6.517174, "FunctionSpace": 0.415331, "Solve": 47.785884, "problem": "Elastic", "nodes": 2}, {"Create boundary conditions": 0.073361, "Create RHS function": 0.405785, "Assemble matrix": 4.852739, "Assemble vector": 0.191505, "Create Mesh": 7.025687, "FunctionSpace": 0.429397, "Solve": 52.79972, "problem": "Elastic", "nodes": 4}, {"Create boundary conditions": 0.074222, "Create RHS function": 0.412209, "Assemble matrix": 5.063124, "Assemble vector": 0.194609, "Create Mesh": 8.489121, "FunctionSpace": 0.462497, "Solve": 51.81542, "problem": "Elastic", "nodes": 8}, {"Create boundary conditions": 0.229184, "Create RHS function": 1.610209, "Assemble matrix": 2.916517, "Assemble vector": 0.457012, "Create Mesh": 21.692559, "FunctionSpace": 1.669815, "Solve": 34.266531, "problem": "Poisson", "nodes": 16}, {"Create boundary conditions": 0.217678, "Create RHS function": 1.553121, "Assemble matrix": 2.526801, "Assemble vector": 0.444187, "Create Mesh": 12.977384, "FunctionSpace": 1.210414, "Solve": 24.222331, "problem": "Poisson", "nodes": 1}, {"Create boundary conditions": 0.221934, "Create RHS function": 1.536028, "Assemble matrix": 2.506988, "Assemble vector": 0.434258, "Create Mesh": 14.162872, "FunctionSpace": 1.21067, "Solve": 30.699727, "problem": "Poisson", "nodes": 2}, {"Create boundary conditions": 0.224337, "Create RHS function": 1.563413, "Assemble matrix": 2.571688, "Assemble vector": 0.440446, "Create Mesh": 15.647355, "FunctionSpace": 1.307196, "Solve": 31.941634, "problem": "Poisson", "nodes": 4}, {"Create boundary conditions": 0.235026, "Create RHS function": 1.634913, "Assemble matrix": 2.883323, "Assemble vector": 0.466077, "Create Mesh": 18.371215, "FunctionSpace": 1.666536, "Solve": 33.483023, "problem": "Poisson", "nodes": 8}]}, {"time": "2021-06-05 10:57:26.445422", "machine": "csd3", "data": [{"Create boundary conditions": 0.081873, "Create RHS function": 0.412572, "Assemble matrix": 5.489823, "Assemble vector": 0.187981, "Create Mesh": 9.379958, "FunctionSpace": 0.554133, "Solve": 59.333637, "problem": "Elastic", "nodes": 16}, {"Create boundary conditions": 0.064321, "Create RHS function": 0.404263, "Assemble matrix": 4.73659, "Assemble vector": 0.189051, "Create Mesh": 6.415966, "FunctionSpace": 0.344774, "Solve": 44.370841, "problem": "Elastic", "nodes": 1}, {"Create boundary conditions": 0.072238, "Create RHS function": 0.404967, "Assemble matrix": 4.762261, "Assemble vector": 0.180542, "Create Mesh": 5.16588, "FunctionSpace": 0.414892, "Solve": 47.888108, "problem": "Elastic", "nodes": 2}, {"Create boundary conditions": 0.075609, "Create RHS function": 0.409027, "Assemble matrix": 4.945373, "Assemble vector": 0.183728, "Create Mesh": 6.017306, "FunctionSpace": 0.432271, "Solve": 52.796065, "problem": "Elastic", "nodes": 4}, {"Create boundary conditions": 0.073947, "Create RHS function": 0.422361, "Assemble matrix": 5.520416, "Assemble vector": 0.189158, "Create Mesh": 7.827057, "FunctionSpace": 0.491648, "Solve": 54.138246, "problem": "Elastic", "nodes": 8}, {"Create boundary conditions": 0.230507, "Create RHS function": 1.598852, "Assemble matrix": 2.896859, "Assemble vector": 0.425873, "Create Mesh": 21.246628, "FunctionSpace": 1.682273, "Solve": 34.080754, "problem": "Poisson", "nodes": 16}, {"Create boundary conditions": 0.217505, "Create RHS function": 1.553404, "Assemble matrix": 2.6052, "Assemble vector": 0.411358, "Create Mesh": 13.407684, "FunctionSpace": 1.195221, "Solve": 24.170464, "problem": "Poisson", "nodes": 1}, {"Create boundary conditions": 0.22178, "Create RHS function": 1.5348, "Assemble matrix": 2.513885, "Assemble vector": 0.410583, "Create Mesh": 14.162559, "FunctionSpace": 1.214346, "Solve": 30.761786, "problem": "Poisson", "nodes": 2}, {"Create boundary conditions": 0.224172, "Create RHS function": 1.565813, "Assemble matrix": 2.574107, "Assemble vector": 0.411415, "Create Mesh": 15.612092, "FunctionSpace": 1.294078, "Solve": 31.995765, "problem": "Poisson", "nodes": 4}, {"Create boundary conditions": 0.232788, "Create RHS function": 1.634892, "Assemble matrix": 2.924821, "Assemble vector": 0.431927, "Create Mesh": 17.707723, "FunctionSpace": 1.638646, "Solve": 31.675879, "problem": "Poisson", "nodes": 8}]}, {"time": "2021-06-09 05:30:25.288069", "machine": "csd3", "data": [{"Create boundary conditions": 0.076699, "Create RHS function": 0.40529, "Assemble matrix": 5.552084, "Assemble vector": 0.185532, "Create Mesh": 7.864297, "FunctionSpace": 0.547028, "Solve": 55.901347, "problem": "Elastic", "nodes": 16}, {"Create boundary conditions": 0.063334, "Create RHS function": 0.402919, "Assemble matrix": 4.733854, "Assemble vector": 0.186641, "Create Mesh": 6.579449, "FunctionSpace": 0.338371, "Solve": 44.132028, "problem": "Elastic", "nodes": 1}, {"Create boundary conditions": 0.073408, "Create RHS function": 0.407318, "Assemble matrix": 4.878275, "Assemble vector": 0.182593, "Create Mesh": 6.498291, "FunctionSpace": 0.419584, "Solve": 47.874968, "problem": "Elastic", "nodes": 2}, {"Create boundary conditions": 0.074014, "Create RHS function": 0.41834, "Assemble matrix": 5.426377, "Assemble vector": 0.187676, "Create Mesh": 7.84575, "FunctionSpace": 0.48611, "Solve": 55.960681, "problem": "Elastic", "nodes": 4}, {"Create boundary conditions": 0.072193, "Create RHS function": 0.403679, "Assemble matrix": 4.931486, "Assemble vector": 0.184527, "Create Mesh": 8.622764, "FunctionSpace": 0.454047, "Solve": 50.327331, "problem": "Elastic", "nodes": 8}, {"Create boundary conditions": 0.225411, "Create RHS function": 1.603077, "Assemble matrix": 2.894772, "Assemble vector": 0.422419, "Create Mesh": 21.472864, "FunctionSpace": 1.660996, "Solve": 33.404734, "problem": "Poisson", "nodes": 16}, {"Create boundary conditions": 0.21945, "Create RHS function": 1.582966, "Assemble matrix": 2.53562, "Assemble vector": 0.415511, "Create Mesh": 14.047362, "FunctionSpace": 1.180673, "Solve": 24.430812, "problem": "Poisson", "nodes": 1}, {"Create boundary conditions": 0.21686, "Create RHS function": 1.568269, "Assemble matrix": 2.769592, "Assemble vector": 0.40984, "Create Mesh": 14.056364, "FunctionSpace": 1.241841, "Solve": 30.471933, "problem": "Poisson", "nodes": 2}, {"Create boundary conditions": 0.228174, "Create RHS function": 1.637089, "Assemble matrix": 2.847215, "Assemble vector": 0.441095, "Create Mesh": 17.147225, "FunctionSpace": 1.412309, "Solve": 32.532815, "problem": "Poisson", "nodes": 4}, {"Create boundary conditions": 0.240317, "Create RHS function": 1.591158, "Assemble matrix": 2.59608, "Assemble vector": 0.412529, "Create Mesh": 17.964989, "FunctionSpace": 1.454856, "Solve": 30.172105, "problem": "Poisson", "nodes": 8}]}, {"time": "2021-06-12 05:23:51.352422", "machine": "csd3", "data": [{"Create boundary conditions": 0.074257, "Create RHS function": 0.403567, "Assemble matrix": 5.471125, "Assemble vector": 0.186523, "Create Mesh": 8.780196, "FunctionSpace": 0.494744, "Solve": 54.3624, "problem": "Elastic", "nodes": 16}, {"Create boundary conditions": 0.064538, "Create RHS function": 0.401077, "Assemble matrix": 4.787912, "Assemble vector": 0.18686, "Create Mesh": 6.848685, "FunctionSpace": 0.340883, "Solve": 44.613504, "problem": "Elastic", "nodes": 1}, {"Create boundary conditions": 0.072353, "Create RHS function": 0.406184, "Assemble matrix": 4.886311, "Assemble vector": 0.180617, "Create Mesh": 5.678405, "FunctionSpace": 0.42316, "Solve": 47.047579, "problem": "Elastic", "nodes": 2}, {"Create boundary conditions": 0.071551, "Create RHS function": 0.403563, "Assemble matrix": 4.918332, "Assemble vector": 0.182853, "Create Mesh": 7.274451, "FunctionSpace": 0.427494, "Solve": 52.486911, "problem": "Elastic", "nodes": 4}, {"Create boundary conditions": 0.07388, "Create RHS function": 0.404915, "Assemble matrix": 4.967518, "Assemble vector": 0.185444, "Create Mesh": 9.079901, "FunctionSpace": 0.454297, "Solve": 50.851134, "problem": "Elastic", "nodes": 8}, {"Create boundary conditions": 0.223413, "Create RHS function": 1.586105, "Assemble matrix": 2.67665, "Assemble vector": 0.416318, "Create Mesh": 21.442748, "FunctionSpace": 1.51951, "Solve": 33.233974, "problem": "Poisson", "nodes": 16}, {"Create boundary conditions": 0.214869, "Create RHS function": 1.569926, "Assemble matrix": 2.505693, "Assemble vector": 0.414684, "Create Mesh": 14.855998, "FunctionSpace": 1.203737, "Solve": 24.480758, "problem": "Poisson", "nodes": 1}, {"Create boundary conditions": 0.217227, "Create RHS function": 1.548819, "Assemble matrix": 2.523454, "Assemble vector": 0.409044, "Create Mesh": 15.8511, "FunctionSpace": 1.222962, "Solve": 30.198323, "problem": "Poisson", "nodes": 2}, {"Create boundary conditions": 0.222753, "Create RHS function": 1.559228, "Assemble matrix": 2.65523, "Assemble vector": 0.411328, "Create Mesh": 17.508728, "FunctionSpace": 1.322015, "Solve": 32.057156, "problem": "Poisson", "nodes": 4}, {"Create boundary conditions": 0.226448, "Create RHS function": 1.574486, "Assemble matrix": 2.606395, "Assemble vector": 0.413203, "Create Mesh": 17.29791, "FunctionSpace": 1.489285, "Solve": 31.258034, "problem": "Poisson", "nodes": 8}]}]